petit_ts/__init__.py
petit_ts/handlers.py
petit_ts/ts_store.py
petit_ts-0.2.2.dist-info/LICENSE.txt
petit_ts-0.2.2.dist-info/METADATA
petit_ts-0.2.2.dist-info/WHEEL
petit_ts-0.2.2.dist-info/top_level.txt
petit_ts-0.2.2.dist-info/RECORD
