Metadata-Version: 2.1
Name: petit-ts
Version: 0.2.2
Summary: Convert your python types to typescript
Home-page: https://github.com/Plawn/petit_ts
Author: Plawn
Author-email: plawn.yay@gmail.com
License: apache-2.0
Platform: UNKNOWN
Requires-Python: >=3.8
Requires-Dist: petit-type-system (>=0.3.0)
